heliosFR.pypy37-pp73-x86_64-linux-gnu.so
heliosFR.libs/libgomp-f7e03b3e.so.1.0.0
heliosFR-0.3.1.dist-info/RECORD
heliosFR-0.3.1.dist-info/METADATA
heliosFR-0.3.1.dist-info/LICENSE
heliosFR-0.3.1.dist-info/top_level.txt
heliosFR-0.3.1.dist-info/WHEEL
