Metadata-Version: 2.1
Name: heliosFR
Version: 0.3.1
Summary: Experimental library to visualize complex networks
Home-page: https://github.com/heliosnet/helios-core
Author: Filipi N. Silva
Author-email: filsilva@iu.edu
License: UNKNOWN
Platform: UNKNOWN
Classifier: Programming Language :: Python :: 3
Classifier: License :: OSI Approved :: MIT License
Classifier: Operating System :: MacOS :: MacOS X
Classifier: Operating System :: Microsoft :: Windows
Classifier: Operating System :: POSIX :: Linux
Classifier: Development Status :: 3 - Alpha
Classifier: Programming Language :: C
Classifier: Topic :: Scientific/Engineering :: Visualization
Classifier: Intended Audience :: Science/Research
Requires-Python: >=3.6
